{
    "Code": "ru",
    "Keys": [
        {
            "Key": "main.button.play",
            "Value": "Играть"
        },
        {
            "Key": "main.button.settings",
            "Value": "Настройки"
        },
        {
            "Key": "main.button.return",
            "Value": "Назад"
        },
        {
            "Key": "main.button.exit",
            "Value": "Выйти"
        },
        {
            "Key": "settings.language",
            "Value": "Язык"
        },
        {
            "Key": "main.button.new_game",
            "Value": "Новая Игра"
        },
        {
            "Key": "game.button.exit",
            "Value": "Выйти"
        },
        {
            "Key": "game.button.save",
            "Value": "Сохранить"
        },
        {
            "Key": "main.button.load_last",
            "Value": "Продолжить"
        },
        {
            "Key": "save.text.on_delete",
            "Value": "Вы уверены?"
        },
        {
            "Key": "main.button.load",
            "Value": "Загрузить"
        },
        {
            "Key": "npc.bored.query",
            "Value": "Я скучный Василий, дайте мне скучной еды"
        },
        {
            "Key": "npc.bored.decline",
            "Value": "Слишком интересная!"
        },
        {
            "Key": "npc.bored.accept",
            "Value": "Какая скучная, пойду скучать дальше!"
        },
        {
            "Key": "npc.cool.query",
            "Value": "Я придирчивый Василий, дайте мне крутой пирожок!"
        },
        {
            "Key": "npc.cool.decline",
            "Value": "Какой-то он не крутой"
        },
        {
            "Key": "npc.cool.accept",
            "Value": "Йоу, круто!"
        },
        {
            "Key": "npc.fat.query",
            "Value": "МЯСА"
        },
        {
            "Key": "npc.fat.decline",
            "Value": "БЕ..."
        },
        {
            "Key": "npc.fat.accept",
            "Value": "ММММ"
        },
        {
            "Key": "npc.long.query",
            "Value": "Дайте мне длинной еды, чтобы я стал еще длиннее"
        },
        {
            "Key": "npc.long.decline",
            "Value": "Эта еда слишком короткая"
        },
        {
            "Key": "npc.long.accept",
            "Value": "Какая длинная!"
        },
        {
            "Key": "quest.serve_customers",
            "Value": "Обслуживайте клиентов"
        },
        {
            "Key": "quest.perfect_actions",
            "Value": "Совершайте идеальные действия"
        },
        {
            "Key": "quest.completed",
            "Value": "(Завершено!)"
        },
        {
            "Key": "game.quest",
            "Value": "Задачи"
        },
        {
            "Key": "magazine.buy_more_lamps",
            "Value": "Купить больше ламп"
        },
        {
            "Key": "magazine.buy_bucket",
            "Value": "Купить корзину"
        },
        {
            "Key": "magazine_buy_more_tables",
            "Value": "Купить больше столов"
        },
        {
            "Key": "game.to_oven",
            "Value": "В печь"
        },
        {
            "Key": "cinnabon.query",
            "Value": "Дайте-ка мне рулет-синнабон с джемом! У меня очень тонкий вкус"
        },
        {
            "Key": "cinnabon.decline",
            "Value": "Моя жажда синнабонов не удалена"
        },
        {
            "Key": "cinnabon.accept",
            "Value": "Спасибо, я запомню этот синнабон навсегда!"
        },
        {
            "Key": "main.button.tutorial",
            "Value": "Обучение"
        },
        {
            "Key": "tutorial",
            "Value": "Обучение:   \nУправление скалкой: ЛКМ - тащить, ПКМ - раскатывать. Все рецепты начинаются с раскатанного теста.  \n\nУправление тестом: ЛКМ - протянуть (стрелочка в рецепте), ПКМ - нажать (кружок в рецепте), ЛКМ + ПКМ - перетащить чтобы положить в печь.   \n\nУправление противнем: ЛКМ по противню - задвинуть/вытащиить из печи, ЛКМ по пирожку когда противень снаружи - положить пирожок на полку \n\nУправление полкой: Тащить ЛКМ с пирожком на покупателя - продать \n\nУправление книгой рецептов: Тащить ЛКМ с угла страницы - перелистнуть. Нажать ЛКМ на кнопку под рецептом - выбрать рецепт"
        }
    ]
}